setup.py
rasterfairy/__init__.py
rasterfairy/coonswarp.py
rasterfairy/images2gif.py
rasterfairy/prime.py
rasterfairy/rasterfairy.py
rasterfairy/rfoptimizer.py
rasterfairy/setup.py
rasterfairy.egg-info/PKG-INFO
rasterfairy.egg-info/SOURCES.txt
rasterfairy.egg-info/dependency_links.txt
rasterfairy.egg-info/requires.txt
rasterfairy.egg-info/top_level.txt