Metadata-Version: 2.1
Name: rasterfairy
Version: 1.0.6
Summary: Transform a 2D point cloud into a regular raster
Home-page: https://github.com/quasimondo/RasterFairy
Author: Mario Klingemann
Author-email: quasimondo@gmail.com
License: GNU GPL v3
Keywords: machine-learning raster assignment
Platform: UNKNOWN
Classifier: Development Status :: 3 - Alpha
Classifier: Intended Audience :: Developers
Classifier: Topic :: Software Development :: Build Tools
Classifier: License :: OSI Approved :: MIT License
Classifier: Programming Language :: Python :: 2
Classifier: Programming Language :: Python :: 2.6
Classifier: Programming Language :: Python :: 2.7
Classifier: Programming Language :: Python :: 3
Classifier: Programming Language :: Python :: 3.3
Classifier: Programming Language :: Python :: 3.4
Classifier: Programming Language :: Python :: 3.5
Provides-Extra: test
Provides-Extra: dev
